aquasec_cli/__init__.py
aquasec_cli/_version.py
aquasec_cli/main.py
aquasec_cli/utils.py
aquasec_cli/commands/__init__.py
aquasec_cli/commands/api.py
aquasec_cli/commands/report.py
aquasec_cli-0.0.6.dist-info/LICENSE
aquasec_cli-0.0.6.dist-info/METADATA
aquasec_cli-0.0.6.dist-info/WHEEL
aquasec_cli-0.0.6.dist-info/entry_points.txt
aquasec_cli-0.0.6.dist-info/top_level.txt
aquasec_cli-0.0.6.dist-info/zip-safe
aquasec_cli-0.0.6.dist-info/RECORD
