Metadata-Version: 2.1
Name: aquasec-cli
Version: 0.0.6
Summary: Aqua Security cli
Author: atav928
Author-email: atav928 <dev@tavnets.com>
License: GNU GENERAL PUBLIC LICENSE
Project-URL: repository, https://github.com/atav928/aquasec-cli
Keywords: aquasec,aqua security,workload protection
Classifier: Programming Language :: Python :: 3
Requires-Python: >=3.8
License-File: LICENSE
Requires-Dist: aquasec-api (==0.0.4)
Requires-Dist: click (>=8.1.3)
Requires-Dist: dataclasses (>=0.6)
Requires-Dist: PyYAML (>=6.0)
Requires-Dist: importlib-metadata ; python_version < "3.8"
